generalagents/__init__.py
generalagents/action.py
generalagents/agent.py
generalagents/macos/__init__.py
generalagents/macos/computer.py
generalagents-0.1.1.dist-info/METADATA
generalagents-0.1.1.dist-info/WHEEL
generalagents-0.1.1.dist-info/licenses/LICENSE
generalagents-0.1.1.dist-info/RECORD
