Metadata-Version: 2.4
Name: generalagents
Version: 0.1.1
Summary: General Agents client library
Project-URL: Homepage, https://github.com/generalagents/generalagents
Project-URL: Repository, https://github.com/generalagents/generalagents
Project-URL: Documentation, https://docs.generalagents.com
Author-email: General Agents <dev@generalagents.com>
License-File: LICENSE
Keywords: python
Classifier: Intended Audience :: Developers
Classifier: Programming Language :: Python
Classifier: Programming Language :: Python :: 3
Classifier: Programming Language :: Python :: 3.10
Classifier: Programming Language :: Python :: 3.11
Classifier: Programming Language :: Python :: 3.12
Classifier: Programming Language :: Python :: 3.13
Classifier: Topic :: Software Development :: Libraries :: Python Modules
Requires-Python: >=3.10
Requires-Dist: cattrs>=24.1.3
Requires-Dist: httpx>=0.28.1
Requires-Dist: pillow>=11.1.0
Requires-Dist: pyautogui>=0.9.54
